{"attachments":[],"text":"Уважаем(и/а) Потребител Потребител,\n\nПо повод ваша заявка, регистрирана под номер #220313 със следното описание:\n\nБЛАГОДАРЯ\n\nСледното решение беше намерено:\n\nЗдравейте, Екипът на Сървис Деск Ви благодари за обратната връзка. С пожелания за успешен ден!\n\n \n\nВ случай, че имате нужда от допълнителна помощ, моля регистрирайте нова заявка в СД на АМ. Ако добавяте нова кореспонденция към вече решена или приключена от нас заявка, е възможно да не получите отговор. Моля потвърдете полученото решение, като се разпишете в https://servicedesk.customs.bg и изберете чек бокс \"\"Съгласен съм с решението\"\". В случай, че не го направите, Вашата заявка ще бъде автоматично приключена след 7 дни.\n\n \n\nПоздрави!\n\nЕкипът на СД на АМ","subject":"Намерено е решение на заявка #220313","date":"2024-08-15T09:49:21.000Z","to":[{"address":"tbl_ood@mail.bg","name":""}],"attachmentsData":[]}