{"attachments":["гфо-стат_2012год_-корег-ILONKA.xls"],"text":"-------------------------------------\nSPA преживявания - минерална вода, физотерапия и...почивка в Родопите.\nЗдраве и близост с природата! Минерален външен басейн, вкл. закуска!\nСтилен, модерен и уютен СПА хотел, защото релаксът не трябва да е лукс!\n<http://ads.mail.bg/delivery/ck.php?oaparams=2__bannerid=1533__zoneid=35__OXLCA=1__cb=04ee1834c4__oadest=http%3A%2F%2Fwww.ismena.bg%2Fgaleriya%2F>","subject":"OT4ET","date":"2013-06-17T08:09:37.000Z","to":[{"address":"tbl_ood@mail.bg","name":""}],"attachmentsData":["Б А Л А Н С\nна\n\"ТИБИЕЛ\" ЕООД\nадрес\nобласт ПЕРНИК   град ПЕРНИК   площад \"СВЕТИ ИВАН РИЛСКИ\" № 1\nкъм\n31.12.2012 год.\nА К Т И В\nП А С И В\nРаздели, групи, статии\nБел.\nСума\n(хил.лева)\nРаздели, групи, статии\nБел.\nСума\n(хил.лева)\nтекуща година\nпредходна година\nтекуща година\nпредходна година\nа\n1\n2\nа\n1\n2\nА.\nЗаписан, но невнесен капитал\nА.\nСобствен капитал\n5\n5\nБ.\nНетекущи (дълготрайни) активи\nI.\nЗаписан капитал\n5\n5\nІ.\nНематериални активи\nІІ.\nПремии от емисии\nПродукти от развойна дейност\nІІІ.\nРезерв от посредващи оценки\nКонцесии, патенти, лицензии, търговски марки, програмни продукти и други подобни права и активи\nІV.\nРезерви\nТърговска репутация\nЗаконови резерви\nПредоставени аванси и нематериални активи в процес на изграждане\nРезерв, свързан с изкупени собствени акции\nОбщо за група I:\nРезерв съгласно учредителен акт\nIІ.\nДълготрайни материални активи\nДруги резерви\nЗеми и сгради, в т. ч.:\n120\nОбщо за група ІV:\n- земи\nV.\nНатрупана печалба (загуба) от минали години, в т. ч.:\n- сгради\n120\n- неразпределена печалба\n2232\nМашини, производствено оборудване и апаратура\n66\n- непокрита загуба\nСъоръжения и други\n202\nОбщо за група V:\n2232\nПредоставени аванси и дълготрайни материални активи в процес на изграждане\n68\nVІ.\nТекуща печалба (загуба)\n16318\n2242\nОбщо за група IІ:\n456\nОбщо раздел А:\n18555\n2247\nIII.\nДългосрочни финансови активи\nБ.\nПровизии и сходни задължения\nАкции и дялове в предприятия от група\nПровизии за пенсии и други подобни задължения\nПредоставени заеми на предприятия от група\nПровизии за данъци, в т. ч.:\nАкции и дялове в асоциирани и смесени предприятия\n- отсрочени данъци\nПредоставени заеми, свързани с асоциирани и смесени предприятия\nДруги провизии и сходни задължения\nДългосрочни инвестиции\n104\nОбщо за раздел Б:\nДруги заеми\n24184\n11907\nВ.\nЗадължения\nИзкупени собствени акции\nОблигационни заеми с отделно посочване на конвертируемите,  в т. ч.:\n- номинална стойност ....................хил. лв.\n- до 1 година\nОбщо за група ІІІ:\n24288\n11907\n- над 1 година\nІV.\nОтсрочени данъци\n1\nЗадължения към финансови предприятия,  в т. ч.:\nОбщо за раздел Б:\n24745\n11907\n- до 1 година\nВ.\nТекущи (краткотрайни) активи\n- над 1 година\nI.\nМатериални запаси\nПолучени аванси, в т. ч.:\n105\nСуровини и материали\n81\n- до 1 година\n105\nНезавършено производство\n- над 1 година\nПродукция и стоки, в т. ч.:\n3\nЗадължения към доставчици, в т. ч.:\n22140\n11085\n- продукция\n- до 1 година\n22140\n11085\n- стоки\n3\n- над 1 година\nПредоставени аванси\nЗадължения по полици, в т. ч.:\nОбщо за група І:\n84\n- до 1 година\nII.\nВземания\n- над 1 година\nВземания от клиенти и доставчици, в т. ч.: 499\n16162\n3294\nЗадължения към предприятия от група,  в т. ч.:\n- над 1 година\n- до 1 година\nВземания от предприятия от група, в т. ч.:\n- над 1 година\n- над 1 година\nЗадължения, свързани с асоциирани и смесени предприятия,  в т. ч.:\nВземания, свързани с асоциирани и смесени предприятия, в т.ч.:\n- до 1 година\n- над 1 година\n- над 1 година\n\n1181\n9\nДруги задължения,  в т. ч.:\n1963\n1882\n- над 1 година\n- до 1 година\n1963\n1882\nОбщо за група II:\n17343\n3303\n- над 1 година\nIII.\nИнвестиции\n- към персонала,  в т. ч.:\n25\n3\nАкции и дялове в предприятия от група\n- до 1 година\n25\n3\nИзкупени собствени акции\n- над 1 година\n- номинална стойност.......................хил. лв.\n- осигурителни задължения в  в т. :\n9\n1\nДруги инвестиции\n- до 1 година\n9\n1\nОбщо за група III:\n- над 1 година\nIV.\nПарични средства, в т. ч.:\n4\n- данъчни задължения,  в т. ч.:\n1929\n874\n- в брой\n4\n2\n- до 1 година\n1929\n874\n- в безсрочни сметки (депозити)\n587\n2\n- над 1 година\nОбщо за група IV:\n591\n4\nОбщо раздел В,  в т. ч.:\n24208\n12967\nОбщо за раздел В:\n18018\n3307\n- до 1 година\n24208\n12967\nГ.\nРазходи за бъдещи периоди\n- над 1 година\nГ.\nФинансирания и приходи за бъдещи периоди,  в т. ч.:\n- финансирания\n- приходи за бъдещи периоди\nСума на актива (А+Б+В+Г)\n42763\n15214\nСума на пасива (А+Б+В+Г)\n42763\n15214\nВ.\nУсловни активи\nГ.\nУсловни пасиви\nДата:\nСъставител:\nРъководител: Димитър Иванов\nОТЧЕТ ЗА ПРИХОДИТЕ И РАЗХОДИТЕ\nна\n\"ТИБИЕЛ\" ЕООД\nадрес\nобласт ПЕРНИК   град ПЕРНИК   площад \"СВЕТИ ИВАН РИЛСКИ\" № 1\nза\n31.12.2012 год.\nНаименование на разходите\nСума\n(хил. лeвa)\nНаименование на приходите\nСума\n(хил. лeвa)\nтекуща година\nпредходна година\nтекуща година\nпредходна година\nа\n1\n2\na\n1\n2\nА. Разходи\nБ.Приходи\nI\nНамаление на запасите от продукция и незавършено производство\nI.\nНетни приходи от продажби, в т.ч.:\n116200\n47261\nII\nРазходи за суровини, материали и външни услуги, в т. ч.:\n1228\n4\nа) продукция\n383\nа) суровини и материали\n196\nб) стоки\n114785\n47261\nб) външни услуги\n1032\n4\nв) услуги\n1032\nIII\nРазходи за персонала, в т. ч.:\n161\n17\nII.\nУвеличение на запасите от продукция и незавършено производство\nа) разходи за възнаграждения\n134\n14\nIII.\nРазходи за придобиване на активи по стопански начин\nб) разходи за осигуровки, в т. ч.:\n27\n3\nIV\nДруги приходи, в т.ч.:\n11199\n- осигуровки, свързани с пенсии\n20\n2\n- приходи от финансирания\nIV\nРазходи за амортизация и обезценка, в т. ч.:\n9\nОбщо приходи от оперативна дейност (I + II + III + IV)\n127399\n47261\nа) разходи за амортизация и обезцинка на дълготрайни материални и нематериални активи, в т. ч.:\n9\nV\nПриходи от участия в дъщерни, асоциирани и смесени предприятия, в т.ч.:\n- разходи за амортизация\n9\n- приходи от участия в предприятия от група\n- разходи от обезценка\nVI\nПриходи от други инвестиции и заеми, признати като нетекущи (дългосрочни) активи, в т.ч.:\nб) разходи от обезцетка на текущи (краткотрайни) активи\n- приходи от предприятия от група\nV\nДруги разходи, в т. ч.:\n108960\n44620\nVII\nДруги лихви и финансови приходи, в т.ч.:\n1162\n9\nа) балансова стойност на продадените активи\n105448\n42618\nа) приходи от предприятия от група\nб) провизии\nб) положителни разлики от операции с финансови активи\nОбщо разходи за оперативна дейност (1+2+3+4+5):\n110358\n44641\nв) положителни разлики от промяна на валутни курсове\nVI\nРазходи от обезценка на финансови активи, включително инвестициите, признати като текущи (краткосрочни) активи, в т. ч.:\n1\nОбщо финансови приходи (5+6+7)\n1162\n9\n- отрицателни разлиси от промяна на валутните курсове\n1\n8. Загуба от обичайната дейност\nVII\nРазходи за лихви и други финансови разходи, в т.ч.:\n68\n5\n9. Извънредни приходи\nа) разходи, свързани с предприятия от група\nб) отрицателни разлики от операции с финансови активи\nОбщо финансови разходи (6+7):\n69\n5\nVIII\nПечалба от обичайната дейност\n18134\n2624\nIX\nИзвънредни разходи\nОбщо разходи(1+2+3+4+5+6+7+9):\n110427\n44646\nОбщо приходи(1+2+3+4+5+6+7+9)\n128561\n47270\nX. Счетоводна печалба (общо приходи - общо разходи)\n18134\n2624\n10. Счетоводна загуба (общо приходи - общо разходи)\nXI. Разходи за данъци от печалбата\n1816\n382\nXII. Други данъци, алтернративни на корпоративния данък\nXIII. Печалба (Б-В-Г)\n16318\n2242\n11. Загуба (10 + ред 11 и 12 от Раздел А )\nВсичко (Общо разходи В + Г + Д)\n128561\n47270\nВсичко (Общо приходи + 11)\n128561\n47270\nДата:\nСъставител:\nРъководител: Димитър Иванов\nОТЧЕТ ЗА ПАРИЧНИТЕ ПОТОЦИ ПО ПРЕКИЯ МЕТОД\nна\n\"ТИБИЕЛ\" ЕООД\nадрес\nобласт ПЕРНИК   град ПЕРНИК   площад \"СВЕТИ ИВАН РИЛСКИ\" № 1\nза\n31.12.2012 год.\n(xил. лева)\nНаименование на паричните потоци\nТекущ период\nПредходен период\nпостъпле-ния\nплащания\nнетен поток\nпостъпле-ния\nплащания\nнетен поток\nа\n1\n2\n3\n4\n5\n6\nА. Парични потоци от основната дейност\nПарични потоци, свързани с търговски контрагенти\n104926\n90917\n14009\n53419\n40493\n12926\nПарични потоци, свързани с краткосрочни финансови активи, държани за търговски цели\nПарични потоци, свързани с трудови възнаграждения\n132\n-132\n14\n-14\nПарични потоци, свързани с лихви, комисионни, дивиденти и други подобни\nПарични потоци от положителни и отрицателни валутни курсови разлики\n1\n-1\nПлатени и възстановени данъци върху печалбата\n387\n-387\nПлащания при разпределения на печалби\nДруги парични потоци от основната дейност\n5\n-5\nВсичко парични потоци от основната дейност (А)\n104926\n91442\n13484\n53419\n40507\n12912\nБ. Парични потоци от инвестиционната дейност\nПарични потоци, свързани с дълготрайни активи\n557\n-557\nПарични потоци, свързани с краткосрочни финансови активи\nПарични потоци, свързани с лихви, комисионни, дивиденти и други подобни\nПарични потоци от бизнескомбинации - придобивания\nПарични потоци от положителни и отрицателни валутни курсови разлики\nДруги парични потоци от инвестиционната дейност\nВсичко парични потоци от инвест. дейност (Б)\n557\n-557\nВ. Парични потоци от финансовата дейност\nПарични потоци от емитиране и обратно придобиване на ценни книжа\nПарични потоци от допълнителни вноски и връщането им на собствениците\nПарични потоци, свързани с получени или предоставени заеми\n7181\n19459\n-12278\n12908\n-12908\nПарични потоци от лихви, комисионни, дивиденти и други подобни\n62\n-62\n5\n-5\nПлащания на задължения по лизингови договори\nПарични потоци от положителни и отрицателни валутни курсови разлики\nДруги парични потоци от финансовата дейност\nВсичко парични потоци от финансовата дейност (В)\n7181\n19521\n-12340\n12913\n-12913\nГ. Изменение на паричните средства през периода (А+Б+В)\n112107\n111520\n587\n53419\n53420\n-1\nД. Парични средства в началото на периода\n4\n5\nЕ. Парични средства в края на периода\n591\n4\nДата:\nРъководител: Димитър Иванов\nОТЧЕТ ЗА СОБСТВЕНИЯ КАПИТАЛ\nна\n\"ТИБИЕЛ\" ЕООД\nадрес\nобласт ПЕРНИК   град ПЕРНИК   площад \"СВЕТИ ИВАН РИЛСКИ\" № 1\nкъм\n31.12.2012 год.\n(хил. лева)\nПоказатели\nЗаписан капитал\nПремии от емисия\nРезерв от последващи оценки\nРезерви\nФинансов резултат от минали години\nТекуща печалба/загуба\nОбщо собствен капитал\nЗаконови\nсвързани с изкупени собствени акции\nсъгласно учредителен акт\nДруги резерви\nНеразпределена печалба\nНепокрита загуба\nа\n1\n2\n3\n4\n5\n6\n7\n8\n9\n10\n11\nА. Салдо в началото на отчетния период\n5\n2362\n2367\nПромени в счетоводната политика\nГрешки\n-130\n-130\nБ. Салдо след промени в счетоводната политика и грешки\n5\n2232\n2237\nИзменения за сметка на собствениците, в т.ч.:\n- увеличение\n- намаление\nФинансов резултат за текущия период\n16318\n16318\nРазпределения на печалбите, в т.ч.:\n2232\n-2232\n- за дивиденти\nПокриване на загуба\nПоследващи оценки на активи и пасиви\n- увеличение\n- намаление\nДруги изменения в собствения капитал\n2232\nВ. Салдо към края на отчетния период\n5\n2232\n16318\n18555\nПромени от преводи на годишни финансови отчети на предприятия в чужбина\nГ. Собствен капитал към края на отчетния период ( 11+/- 12)\n5\n2232\n16318\n18555\nДата:23.03.2012\nСъставител: Илияна Шопова\nРъководител: Димитър Иванов\nДЪЛГОТРАЙНИ АКТИВИ\n(хил. лева)\nПоказатели\nОтчетна стойност на нетекущите активи:\nПоследваща оценка\nПреоценена стойност (4+5-6)\nАмортизация\nПоследваща оценка\nПреоценена амортизация в края на периода (11+12-13)\nБалансова стойнност в края на периода        (7-14)\nв началото на периода\nна постъпилите през периода\nна излезлите през периода\nв края на периода (1+2-3)\nувеличение\nнамаление\nв началото на периода\nначислена през периода\nотписана през периода\nв края на периода (8+9-10)\nувеличение\nнамаление\nа\n1\n2\n3\n4\n5\n6\n7\n8\n9\n10\n11\n12\n13\n14\n15\nI.\nНематериални активи\n1\nПродукти от развойна дейност\n2\nКонцесии, патенти, лицензии, търговски марки, програмни продукти и други подобни права и активи\n3\nТърговска репутация\n4\nПредоставени аванси и нематериални активи в процес на изграждане\nОбщо за група I:\nII.\nДълготрайни материални активи\n1\nЗеми и сгради, в т.ч.:\n121\n121\n121\n1\n1\n1\n120\n- земи\n- сгради\n121\n121\n121\n1\n1\n1\n120\n2\nМашини, производствено оборудване и апаратура\n70\n70\n70\n4\n4\n4\n66\n3\nСъоръжения и друга\n206\n206\n206\n4\n4\n4\n202\n4\nПредоставени аванси и дълготрайни материални активи в процес на изграждане\n68\n68\n68\n68\nОбщо за група II:\n465\n465\n465\n9\n9\n9\n456\nIII.\nДългосрочни финансови активи\n1\nАкции и дялове в предприятия от група\n104\n104\n104\n104\n2\nПредоставени заеми на предприятия от група\n3\nАкции и дялове в асоциирани и смесени предприятия\n4\nПредоставени заеми, свързани с асоциирани и смесени преприятия\n5\nДългосрочни инвестиции\n104\n104\n104\n104\n6\nДруги заеми\n11907\n12277\n24184\n24184\n24184\n7\nИзкупени собствени акции\nОбщо за група III:\n11907\n12381\n24288\n24288\n24288\nIV.\nОстрочени данъци\n1\n1\n1\n1\nОбщ сбор (I+II+III+IV)\n11907\n12847\n24754\n24754\n9\n9\n9\n24745\nСъставител:\nДата:\nУЧАСТИЯ В КАПИТАЛИ НА ДРУГИ ПРЕДПРИЯТИЯ /ИНВЕСТИЦИИ/\n(xил. лв.)\nНаименоваине и седалище на предприятието, в които са съучастията\nРазмер на съучастието\nПроцент на съучастие в капитала на другото предприятие\nСъучастие в ценни книжа, приети за търговия на фондовата борса\nСъучастие в ценни книжа, неприети за търговия на фондовата борса\nа\n1\n2\n3\n4\nА. В страната\nI. В дъщерни предприятия\n1\n2\n3\n4\nОбща сума I:\nII. В смесени предприятия\n1\n2\n3\n4\nОбща сума II:\nIII. В асоциирани предприятия\n1\n2\n3\n4\nОбща сума III:\nIV. В други предприятия\n1\n2\n3\n4\nОбща сума IV:\nОбщо сума за страната (I+II+II+IV) :\nА. В чужбина\nI. В дъщерни предприятия\n1\n2\n3\n4\nОбща сума I:\nII. В смесени предприятия\n1\n2\n3\n4\nОбща сума II:\nIII. В асоциирани предприятия\n1\n2\n3\n4\nОбща сума III:\nIV. В други предприятия\n1\n2\n3\n4\nОбща сума IV:\nОбщо сума за чужбина (I+II+II+IV) :\nДАНЪЧНИ ВРЕМЕННИ РАЗЛИКИ\n(xил. лeвa)\nВременна разлика\n40908\nДвижение на отсрочените данъци 2012 г.\n41274\nувеличение\nнамаление\nДанъчна основа\nВременна разлика\nДанъчна основа\nВременна разлика\nДанъчна основа\nВременна разлика\nДанъчна основа\nВременна разлика\nАктиви по отсрочени данъци\nАмортизации\nОбезценка\nКомпенсируми отпуски\n1018\n3442.28\n1018\n3442.2800000000007\nЗагуба\nПровизии\n867.12\n4144.71\n867\n4144.83\nОбщо активи:\n1885.12\n7586.99\n1885\n7587.110000000001\nПасиви по отсрочени данъци\nПреоценъчен резерв\nАмортизации\nОбщо пасиви:\nОтсрочени данъци (нето)\n1885.12\n7586.99\n1885\n7587.110000000001\nМАТЕРИАЛНИ ЗАПАСИ\nВидове материални запаси\nГодината завършваща на 31.12.2012г\nГодината завършваща на 31.12.2011г\nМатериали:\n81\nспомагателни м-ли\n36\nрезервни части\n38\nгорива и смазочни м-ли\n3\nММП\n4\nСтоки :\n3\nмагнетит\n3\n.....\nНезавършено производство\nПродукция\nДруги материални запаси\nВсичко материални запаси:\n84\nВЗЕМАНИЯ\nА. ВЗЕМАНИЯ\n(хил. лева)\nПоказатели\nОбщ размер\nСтепен на ликвидност\nдо 1 година\nнад 1 година\nа\n1\n2\n3\nІ. Невнесен капитал\nІІ. Дългосрочни вземания\n1. Вземания от свързани предприятия, в т.ч.:\n- предоставени заеми\n- други\n2. Вземания от предоставени търговски заеми\n25350\n25350\n3. Други дългосрочни вземания в т.ч.:\n- финансов лизинг\n- дългосрочни аванси\n- други\nВсичко за II:\n25350\n25350\nІІІ. Краткосрочни вземания\n1. Вземания от свързани предприятия в т.ч.:\n- предоставени заеми\n- от продажби\n- други\n2. Вземания от клиенти\n14891\n14891\n3. Вземания от предоставени аванси 498 и 402\n1271\n1271\n4. Вземания от предоставени търговски заеми\n5. Съдебни вземания\n6. Присъдени вземания\n7. Данъци за възстановяване в т.ч.:\n- данък за общините\n- данък върху печалбата\n- данък върху добавената стойност\n- възстановени данъчни временни разлики\n- други данъци\n8. Други краткосрочни вземания в т.ч.:\n15\n15\n- по рекламации\n- по липси и начети\n- от социалното осигуряване\n- други\n15\n15\nВсичко за III:\n16177\n16177\nОбщо вземания: (I+II+III)\n41527\n41527\nТЕКУЩИ ФИНАНСОВИ АКТИВИ\n(xил. лв.)\nПоказатели\nВид и брой на ценните книжа\nСтойност на ценните книжа\nобикновени\nпривилегировани\nконвертируеми\nотчетна стойност\nпреоценка\nпреоценена стойност (4+5-6)\nв това число:\nувеличение\nнамаление\nинвестиции от техн. резерви\nинвестиции от други резерви\nа\n1\n2\n3\n4\n5\n6\n7\n8\n9\nІ. Краткосрочни финансови активе в ценни книжа\n1. Акции\n2. Изкупени собствени акции\n3. Облигации\n4. Изкупени собствени облигации\n5. Държавни ценни книжа\nВсичко за I:\nІІ. Дългосрочни финансови активи в ценни книжа\n1. Акции\n2. Облигации\n3. Държавни ценни книжа\n4. Инвестиционни бонове\n5. Други документи и права\nВсичко за III:\nПАРИЧНИ СРЕДСТВА\nПарични средства\nКъм годината завършваща на 31.12.2012\nКъм годината завършваща на 31.12.2011\nПарични средства в брой\n4\n2\nВъв валута\nВ лева\n4\n2\nПарични средства в разплащателни сметки\n587\n2\nВ разплащателни сметки в лева\n587\n2\nВ разплащателни сметки във валута\nБлокирани парични средства\nПарични еквиваленти\nВсичко парични средства:\n591\n4\nСПРАВКА ЗА ФИНАНСОВИТЕ РЕЗУЛТАТИ\n(xил. лeвa)\nПоказатели\nШифър\nСума\nа\nб\n1\nА. Неразпределена печалба\nІ. Неразпределена печалба към 01.01.\n2242\nІІ. Увеличение на неразпределената печалба за сметка на :\n1. Печалбата от предходната година\n2. Приложение на препоръчителния подход за отразяване\nна грешки,промени в счетоводната политика и др.\n3. Прехвърляне на преоценъчен резерв за отписани активи\n4. Други източници\nОбща сума ІІ.\nІІІ. Разпределение на печалбата от минали години :\n1. За покриване на загуба от минали тодини\n2. За резерви\n3. За дивиденти, в т.ч.\n- за държавата\n4. Дарения\n5. Увеличаване на основния капитал\n6. За други цели\n7. Неразпределена печалба\n2232\nОбща сума ІІІ.\n2232\nІV. Неразпределена печалба към 31.12.\nБ. Непокрита загуба\nІ. Непокрита загуба към 01.01.\nІІ. Увеличение на загубата за сметка на :\n1. Прехвърляне на загуба от предходната година\n2. Други\nВсичко ІІ.\nІІІ. Покриване на загуби от минали години за сметка на :\n1. Неразпределан печалба от минали години\n2. Резерви\n3. Основен капитал\nОбща сума ІІІ.\nІV.Непокрита загуба към 31.12.\nВ. Финансов резултат от текущата година\n1. Печалба\n16318\n2. Загуба\nПРОВИЗИИ И СХОДНИ ЗАДЪЛЖЕНИЯ\n(хил. лева)\nПоказатели\nВ началото на годината\nУвеличение\nНамаление\nВ края на годината\nа\n1\n2\n3\n4\n1. Провизии за пенсии и други подобни задължения\n2. Провизии за данъци в т.ч.:\n- отстрочени данъци\n3. Други провизии и сходни задължения\nОбща сума: (1+2+3)\nЗАДЪЛЖЕНИЯ\n(хил. лева)\nПоказатели\nОбщ размер\nСтепен на изискуемост\nСтойност на обезпечението\nдо 1 година\nнад 1 година\nа\n1\n2\n3\n4\nІ. Дългосрочни задължения\n1. Задължения към свързани предприятия, в т.ч. от:\n- заеми\n- доставки на активи и услуги\n2. Задължения по получени банкови заеми, в. т.ч.\n- редовни заеми\n- просрочени до 3 години\n- просрочени над 3 години\n3. Задължения по получени търговски заеми\n4. Задължения по облигационни заеми\n5. Задължения по получени аванси\n6. Отсрочени данъци\n7. Други дългосрочни задължения в т.ч.:\n- финансов лизинг\nВсичко за I:\nІІ. Краткосрочни задължения\n1. Задължения към свързани предприятия, в т.ч. за:\n- доставени активи и услуги\n- дивиденти\n2. Задължения към финансови предприятия, в. т.ч.\n- към банки\n- просрочени\n3. Задължения към доставчици и клиенти\n22140\n4. Задължения по получени търговски заеми\n5. Получени аванси\n105\n6. Задължения към персонала\n25\n7. Задължения към социалното осигуряване\n9\n- социално осигуряване\n6\n- здравно осигуряване\n2\n- други-дзпо\n1\n8. Данъчни задължения в т.ч.:\n1929\n- данък за общините\n3\n- данък върху печалбата\n1811\n- данък върху добавената стойност\n104\nдруги данъци- лихви\n11\n9. Други краткосрочни задължения\nВсичко за II:\n24208\nОбщо задължения: (I+II)\n24208\nСВЪРЗАНИ ЛИЦА\n\nВид на сделката\nСвързано лице доставчик\nГодината приключваща на 31.12.2009\nГодината приключваща на 31.12.2008\nСума в х.лв.\nСума в х.лв.\nВсичко сделки :\nВид на сделката\nСвързано лице клиент\nГодината приключваща на 31.12.2009\nГодината приключваща на 31.12.2008\nСума в х.лв.\nСума в х.лв.\nВсичко сделки:\nДОГОВОРИ ЗА СТРОИТЕЛСТВО\nДОГОВОРИ\nРазходи съответст-ващи на признатите приходи\nОтчетени разходи   срещу които няма признат приход\nНачислени приходи\nНачислени приходи на база етап на завършен договор\nПризнати печалби\nРазмер на получените авансови плащания\nРазмер на задържани средства\nдоговор 1\nдоговор 2\nВсичко строителни договори\nРАЗХОДИ\nВид разход\nГодината приключваща на 31.12.2012\nГодината приключваща на 31.12.2011\nНамаление на запасите от продукция и незавършено производство\nРазходи за суровини, материали и външни услуги в т.ч:\nа/Суровини и материали\n196\nОфис консумативи\n1\nГСМ\n2\nСпомагателни\n1\nрезервни части\n1\nел.енергия\n191\nВсичко разходи за материали:\n196\nб/Разходи за външни услуги:\nПодизпълнители\nРеклама и консултации\n2\nСъобщителни услуги\nНаеми\n2\nЗастраховки\nКуриерски и транспортни\nГраждански договори\n3\nРемонтни услуги\n210\nтранспортни услуги\n807\nодит\n4\nАбонаментна подръжка\n4\nТакси\n2\nдруги\n2\nВсичко разходи за външни услуги:\n1032\n4\nВсичко разходи за материалии външни услуги:\n1228\n4\nРазходи за персонала:\nПроизводствен персонал\n128\n13\nв т.ч. Начислени разходи за неизползвани отпуски\n3\nАдминистративен персонал\n33\n4\nв т.ч. Начислени разходи за неизползвани отпуски\nВсичко разходи за персонала:\n161\n17\nВсичко разходи за амортизации и обезценка:\nа/разходи за амортизация и обезценка на ДМА\n9\nразходи за аморатизации\n9\nразходи за обезценки\nб/разходи за обезценки на текущи активи\nВсичко разходи за амортизация и обезценки:\n9\nДруги разходи в т.ч.\nа/ балансова стойност на продадени активи\n105448\n42618\nб/ провизии\nв/ други в т.ч.\n3512\n2002\nРазходи за командиравки\nРазходи представителни\nРазходи за брак\nРазходи други- неустойки\n3507\n2002\nДанъчно непризнати разходи\nваучери за храна\n5\nВсичко други разходи:\n108960\n44620\nВсичко разходи\n110358\n44641\nПРИХОДИ\nВид на прихода\nГодината приключваща на 31.12.2011\nГодината приключваща на 31.12.2010\nНетни приходи от продажби в т.ч.:\n116200\n47261\nПродажби на продукция\n383\nПродажби на стоки\n114785\n47261\nУслуги\n1032\nПриходи от дългосрочни услуги отчетени по етап на завършен договор\nПриходи от договори за строителство\nДруги услуги\nУвеличение на запасите от продукция и незавършено производство\nРазходи за придобиване на активи по стопански начин\nДруги приходи\n11199\nв т.ч.  от продажба на ДМА\nв. т.ч от продажба на материали\nв. т.ч от наеми\nв т.ч. от възстановени обезценки\nв.т.ч. от отписани задължения\nв т.ч.приходи от финансирания\n9\nдарения свързани с активи\nдарения свързани с приходи\nВсичко приходи от оперативна дейност:\n127399\n47261\nПомощна таблица за изчисляване на финансови показатели\nНАИМЕНОВАНИЕ\nАбрев.\nСтойност, хил.лв\nзабележка / коментар\nФинансов резултат\nФР\n16318\nПриходи от продажби\nПрП\n127399\nРазходи по дейността\nРхД\n110427\nСобствен капитал\nСК\n18555\nПасиви\nПас\n24208\nДългоср. + краткоср.\nСума на реалните активи\nСРАк\n42763\nСума на актив - невн. капитал\nРазходи за данъци\nРД\n1816\nКраткотрайни активи\nКА\n18018\nКраткосрочни задължения\nКЗ\n24208\nТекущи задължения\nТЗ\n24208\nКраткосрочни вземания\nКВз\n17343\nПарични средства\nП\n591\nСредна наличност на КМА\nСНкма\n42\n(МЗкрая - МЗначало) / 2\nМатериални запаси\nМЗ\n84\nКраткоср. фин. активи\nКФА\nПоказател за рентабилност\nстойност\nФормула\nКоефициент на рентабилност \nна ПРИХОДИТЕ ОТ ПРОДАЖБИТЕ\nКРПП\n0.12808577775335755\nФР / ПрП\nКоефициент на рентабилност \nна СОБСТВЕНИЯ КАПИТАЛ\nКРСК\n0.8794395041767717\nФР / СК\nКоефициент на рентабилност \nна ПАСИВИТЕ\nКРПас\n0.674074686054197\nФР / Пас\nКоефициент на рентабилност \nна АКТИВИТЕ\nКРАкт\n0.3815915627996165\nФР / СРАк\nПоказател за ефективност\nстойност\nКоефициент на ефективност\nна РАЗХОДИТЕ\nКЕР\n1.1350284650267723\nПрих / (Разх + РД)\nКоефициент на ефективност\nна ПРИХОДИТЕ\nКЕП\n0.8667807439618835\nРазх / Прих\nПоказател за ликвидност\nстойност\nКоефициент на ОБЩА Ликвидност\nКОЛ\n0.7442994051553206\nКА / КЗ\nКоефициент на БЪРЗА Ликвидност\nКБЛ\n0.7408294778585591\n(КА-МЗ / КЗ\nКоефициент на Незабавна Ликвидност\nКНЛ\n0.7408294778585591\n(КА-МЗ-КФА) / ТЗ\nКоефициент на Абсолютна Ликвидност\nКАЛ\n0.024413417052214142\nП / ТЗ\nПоказател за фин. Автономност\nстойност\nКоефициент на фин. Автономност\nКФА\n0.7664821546596167\nСК / Пас\nКоефициент на задлъжнялост\nКЗ\n1.3046618162220425\nПас / СК\nПоказател за обръщаемост на КМА\nстойност\nВреметраене на 1 оборот, в дни\nВрО\n0.1186822502531417\nСНкма * 360 / Прих\nБрой на оборотите\nБрО\n3033.309523809524\nПрих / СНкма\nЗаетост на КМА\nЗКМА\n0.00032967291736983806\nСНкма  / Прих\nСПРАВКА ЗА ПРИХОДИТЕ И РАЗХОДИТЕ ЗА ЛИХВИ\n(xил. лeвa)\nПоказатели\nСума\nначислени\nплатени / получени\nа\n1\n2\nІ. ПРИХОДИ ОТ ЛИХВИ\n1. Лихви по разплащателни и депозитни сметки\n2. Лихви по предоставени дългосрочни заеми\n3. Лихви по предоставени краткосрочни заеми\n1162\n7\n4. Лихви по търговски заеми\n5. Други лихви\n6. Лихви по депозитни сметки по чл.280 от ТЗ\nОбща сума  (1+2+3+4+5)\n1162\n7\nІІ. РАЗХОДИ ЗА ЛИХВИ\n1. Лихви по краткосрочни заеми, в т.ч. :\n- редовни заеми в левове\n13\n- просрочени заеми в левове\n- редовни заеми във валута\n- просрочени заеми във валута\n2. Лихви по дългосрочни заеми, в т.ч. по:\n- редовни заеми в левове\n- просрочени заеми в левове\n- редовни заеми във валута\n- просрочени заеми във валута\n3. Лихви по дългове, свързани с дялово участие\n4. Лихви по неизплатени заплати в срок\n5. Лихви по държавни вземания\n20\n6. Лихви по търговски задължения\n7. Други лихви\nОбща сума (1+2+3+4+5+6+7)\n20"]}