{"attachments":[],"text":"--\n\n\n----- Препратено писмо от tbl_ood@mail.bg -----\n\nДата: 11.07.2017 в 14:34\nПодател: Брикел ЕАД Пласмент (brikel_plasment@abv.bg)\nОтносно: \nПолучатели: id@tecbd.com, eli@tecbd.com, tbl_ood@mail.bg, otgr@tecbd.com, grand_energy@mail.bg \n\n\n\n-------------------------------------\nПП: Ако имаш идеи за сайт, виж какво предлагат СуперХостинг.БГ. Там ще намериш завършено решение. \n<http://ads.mail.bg/delivery/ck.php?oaparams=2__bannerid=4181__zoneid=35__OXLCA=1__cb=071354665b__oadest=https%3A%2F%2Fwww.superhosting.bg%2Fweb-hosting-compare-hosting-plans.php%3Futm_source%3Dmail.bg%26utm_medium%3Dfooter%26utm_content%3Dv1%26utm_campaign%3Dwebhosting>","subject":"FWD:","date":"2017-07-11T15:07:28.000Z","to":[{"address":"grand_energy@mail.bg","name":""}],"attachmentsData":[]}