{"attachments":["ЕМ-_Ал_Спасов_-превод-10_03_2015.pdf"],"text":"-------------------------------------\nP.S. Взех си хостинг от СуперХостинг.БГ. В момента имат специална зимна промоция със 75% отстъпка. \n<http://ads.mail.bg/delivery/ck.php?oaparams=2__bannerid=3616__zoneid=35__OXLCA=1__cb=920c3d3b6d__oadest=http%3A%2F%2Fwww.superhosting.bg%2Fpromo%2Fwinter2015%3Futm_source%3DMailBG%26utm_medium%3DFooter%26utm_content%3Dv1%26utm_campaign%3DWinter2015>","subject":"получен превод","date":"2015-03-10T12:25:30.000Z","to":[{"address":"evropa.diana@gmail.com","name":""}],"attachmentsData":["Bulbank Online\nстраница 1 от 1\nАВИЗО МЕСТЕН ПРЕВОД\nUniCredit Bulbank\nНомер на операцията / Operation number\n285CHDC150691201\nДата и час на операцията / Operation date time\n10.03.2015 11:57:28\nПлатете на - име на получателя / Beneficiary name\nТИБИЕЛ ЕООД\nIBAN на получателя\nВІС на банката на получателя\nBG66UNCR70001521765243\nUNCRBGSF\nПри банка - име на банката на получателя / Bank Name\nУНИКРЕДИТ БУЛБАНК АД\nПРЕВОДНО НАРЕЖДАНЕ\nВид валута / Currency Сума / Amount\nза кредитен превод\nB GN\n33 560.36\nОснование за плащане - информация за получателя / Details of Payment\nАЛЕКСАНДР АНТОНОВ СПАСОВ 7302202827 ПОГ\nВНОСКА ПО УВЕДОМИТЕЛНО\nПИСМО№ 15/16, 10, 2014 645135797\nОще пояснения / Additional Details\nНаредител - име / Ordering Customer\nBAN на наредителя\nВІС на банката на наредителя\n501100003\nUNCRBGSF\nПри банка - име на банката на наредителя / Bank Name\nУНИКРЕДИТ БУЛБАНК АД\nПлатежная система\nДата на регистрация / Payment system registration date\n10.03.2015\nНомер на регистрация / Payment system registration number\nhttps://online.bulbank.bg/page/?user id=449936&session id=da283b6abc034c03aa0 ... 10.3.2015 r."]}