{"attachments":["2-47.pdf","ТЕЦ_МЗ-М_03_2014_Г.xls"],"text":"-------------------------------------\nMail.BG <http://mail.bg> : Безплатен e-mail адрес. Най-добрите характеристики на българския пазар - 20 GB пощенска кутия, 1 GB прикрепен файл, безплатен POP3, мобилна версия, SMS известяване и други.","subject":"кор.име на у-л","date":"2014-04-03T08:23:38.000Z","to":[{"address":"toncheva@tec-marica3.com","name":""}],"attachmentsData":["ТИБИЕЛ ЕООД\nФАКТУРА ОРИГИНАЛ\n2000000047 / 31.03.2014\nПОЛУЧАТЕЛЯ : ТЕЦ МАРИЦА 3 АД\nДОСТАВЧИК : ТИБИЕЛ ЕООД\nВИН\n: 126526421\nБИН\n: 106588084\nДДС №\n: BG126526421\nДДС №\n: BG106588084\nАДРЕС\n: ДИМИТРОВГРАД, ПРОМИШЛЕНА ЗОНА\nАДРЕС:\n: гр. Перник площад Иван Рилски 1\nОВЕКТ\n:\nOBEKT\n: ТИВИЕЛ ЕООД\nBAHKA\n: OBB AIT\nCMETKA\n: BG08UBBS80021084550130 / UBBSBGSF\nBAHKA\n: Общинска банка АД\nCMETKA\n: BG78SCMB91301051981801 / SOMBBGSF\nNo|\nКод\n=\nАртикул\n|Марка | Количество| Единична Цена |\nСтойності\n11\n0| КЛИЕНТИ ПО АВАНСИ - ТЕЦ МАРИЦА 3 АД\nBP\n1.000|-16 666.08000|\n-16 666.08|\n21\n649| СПЕДИТОРСКИ УСЛУГИ\nт\n3 778.6601\n23.47000|\n88 685.15|\n-\n31\n650 |ТРАНСПОРТНИ ДОБАВЬЧНИ ТАКСИ\nEP\n1.000|\n844.56000|\na44.56|\nRAHBUHA OCHOBA\n72 863.63\nCTABKA HA ZANIKA : 20.00₺\nPASMEP HA JAHLKA\n14 572.73\nBCMYKO :\n87 436.36\nСловом обща сума: /Осемдесет и седем хиляди четиристотин тридесет и шест лева .36/\nПлащане : По Сметка\nДата на данъчно събитие: 31.03.2014\nПРИЕЛ :\nСЪСТАВИЛ :\n/СТОЯН ТЮЙЛИЕВ/\n/ Димитър Иванов/\nЗабележка:\nIntegra Corporate System, Designeg By SmartPro Lad., Varna, tel .: 052/505224\nPage 1 of 1","ОПИС : ТБЛ-ТЕЦ М3-1-03-2014\nДата на описа:\n41729\nгодина\nСПЕДИТОР:\n\"ТИБИЕЛ\"  ЕООД  ПЕРНИК\nКЛИЕНТ:\nТЕЦ МАРИЦА З   АД\n№\nтоварителница\nброй вагони\nотправни\nполучаващи\nза месеца\nфактурирано по авансова ф-ра 2000000001/01.02.2014\nза фактуриране по ф-ра. тегло   /кг/\nпо ред\nномер\nдата\nгара\nгара\nтегло   /кг/\n1\n125\n41715\n18\nСВИЩОВ\nДИМИТРОВГРАД - ЮГ\n919560\n2\n128\n41717\n18\nСВИЩОВ\nДИМИТРОВГРАД - ЮГ\n953060\n3\n133\n41722\n18\nСВИЩОВ\nДИМИТРОВГРАД - ЮГ\n940040\n4\n141\n41724\n18\nСВИЩОВ\nДИМИТРОВГРАД - ЮГ\n966000\nОбщо:\n18\n3778660\nПревозна цена\nевро\n12\nлева\n23.47\nПревозна стойност\n88685.1502\nДобавъчни такси\n844.56\nОблагаема сделка\n89529.7102\n16666.08\n72863.6302\nДДС 20%\n17905.942039999998\n3333.2160000000003\n14572.726039999998\nОбща стойност на фактурата: номер и дата\n2000000046\n41729\n87436.35624\nСПЕДИТОР:........................................\n/ ДИМИТЪР МАЛАКОВ /\nПРИЕЛ :\n..............................\n/ СТОЯН ТЮЙЛИЕВ /"]}