{"attachments":[],"text":"o.k\n\n\n\n--\n\n\n----- Цитат от Minabalkan2000 Цокева (minabalkan2000@abv.bg), на 15.01.2018 в 11:39 -----\n\n\tЗдравейте, на 01.12.2017 г, правите превод в полза на Мина Балкан - 10000.00 лева.Моля да предадете на юристите да направят договор за заем и ни начислете лихвите.Изпратете ни един екземпляр от договора!!!!\n\n\t\n\t\n\n\tУспешна седмица!!!\n\n\n\n-------------------------------------\nMail.BG <http://mail.bg> : Безплатен e-mail адрес. Най-добрите характеристики на българския пазар - 30 GB пощенска кутия, 1 GB прикрепен файл, безплатен POP3, мобилна версия и други.","subject":"RE: Превод 10000 лева","date":"2018-01-15T11:44:42.000Z","to":[{"address":"","name":"Minabalkan2000 Цокева"}],"attachmentsData":[]}