{"attachments":["TIBIEL_EOOD.pdf"],"text":"-- \nThis email has been checked for viruses by Avast antivirus software.\nwww.avast.com","subject":"Fwd: Payment","date":"2024-09-02T13:32:26.000Z","to":[{"address":"","name":"ТИБИЕЛ ЕООД"}],"attachmentsData":["Cari Hesap Ekstresi\nFirma : KUMSAL TRANSPORT LOJ. ULUSLARARASITAŞIMACILIK SAN. TİC. LTD. ŞTİ.\nSayfa No : 1 / 2\nRapor Tarihi : 02.09.2024 - 11:53\nCari Kodu : 120 755\nCari Adı : TIBIEL EOOD\nTarih\nEvrak No\nEvrak Türü\nAçıklama\nDvz. Cinsi\nBor\nAlacak\nBakiye B/A\nVade Tarihi\n01.01.2024\nNakli Yekün\n23.07.2024 TRA2024000000267\nSauş Faturası\n*MANİSA/GALABOVA BG NA\nEURO\n1.700,00\n1.700,00\n23.07.2024\n23.07.2024 TRA2024000000268\nSatış Faturası\n*MANİSA/GALABOVA BG NA\nEURO\n1.700,00\n3.400,00\n23.07.2024\n23.07.2024 TRA2024000000273\nSatış Faturası\nMANİSA/GALABOVA BG NA\nEURO\n1.700,00\n5.100,00\n23.07.2024\n23.07.2024 TRA2024000000274\nSatış Faturası\nMANİSA/GALABOVA BG NA\nEURO\n1.700,00\n6.800,00\n23.07.2024\n26.07.2024 TRA2024000000275\nSatış Faturası\nMANİSA/GALABOVA BG NA\nEURO\n1.700,00\n8.500,00\n26.07.2024\n26.07.2024 TRA2024000000276\nSatış Faturası\nMANİSA/GALABOVA BG NA\nEURO\n1.700,00\n10.200,00\n26.07.2024\n26.07.2024 TRA2024000000277\nSatış Faturası\n*MANİSA/GALABOVA BG NA\nEURO\n1.700,00\n11.900,00\n26.07.2024\n26.07.2024 TRA2024000000278\nSatış Faturası\n*MANİSA/GALABOVA BG NA\nEURO\n1.700,00\n13.600,00\n26.07.2024\n30.07.2024 TRA2024000000284\nSatış Faturası\nMANİSA/GALABOVA BG NA\nEURO\n1.700,00\n15.300,00\n30.07.2024\n30.07.2024 TRA2024000000285\nSatış Faturası\nMANİSA/GALABOVA BG NA\nEURO\n1.700,00\n17.000,00\n30.07.2024\n30.07.2024 TRA2024000000286\nSatış Faturası\n*MANİSA/GALABOVA BG NA\nEURO\n1.700,00\n18.700,00\n30.07.2024\n30.07.2024 TRA2024000000288\nSatış Faturası\n*MANİSA/GALABOVA BG NA\nEURO\n1.700,00\n20.400,00\n30.07.2024\n01.08.2024 TRA2024000000296\nSatış Faturası\nMANİSA/GALABOVA BG NA\nEURO\n1.700,00\n22.100,00\n01.08.2024\n01.08.2024 TRA2024000000297\nSatış Faturası\nMANİSA/GALABOVA BG NA\nEURO\n1.700,00\n23.800,00\n01.08.2024\n01.08.2024 TRA2024000000298\nSatış Faturası\nMANİSA/GALABOVA BG NA\nEURO\n1.700,00\n25.500,00\n01.08.2024\n01.08.2024 TRA2024000000299\nSatış Faturası\nMANİSA/GALABOVA BG NA\nEURO\n1.700,00\n27.200,00\n01.08.2024\n01.08.2024 TRA2024000000300\nSatış Faturası\nMANİSA/GALABOVA BG NA\nEURO\n1.700,00\n28.900,00\n01.08.2024\n02.08.2024\n0000000308\nGelen Havale\nEURO\n13.565,00\n15.335,00\n02.08.2024\n05.08.2024 TRA2024000000305\nSatış Faturası\nMANİSA/GALABOVA BG NA\nEURO\n3.800,00\n19.135,00\n05.08.2024\n05.08.2024 TRA2024000000306\nSatış Faturası\nMANİSA/GALABOVA BG NA\nEURO\n3.800,00\n22.935.00\n05.08.2024\n05.08.2024 TRA2024000000307\nSauş Faturası\n*MANİSA/GALABOVA BG NA\nEURO\n1.700,00\n24.635,00\n05.08.2024\n05.08.2024 TRA2024000000308\nSatış Faturası\nMANİSA/GALABOVA BG NA\nEURO\n1.700,00\n26.335,00\n05.08.2024\n06.08.2024 TRA2024000000313\nSauş Faturası\n*MANİSA/GALABOVA BG NA\nEURO\n1.700,00\n28.035,00\n06.08.2024\n06.08.2024 TRA2024000000314\nSatış Faturası\nMANİSA/GALABOVA BG NA\nEURO\n1.700,00\n29.735,00\n06.08.2024\n06.08.2024 TRA2024000000315\nSatış Faturası\n*MANİSA/GALABOVA BG NA\nEURC\n1.700,00\n31.435,00\n06.08.2024\n07.08.2024\n0000000322\nGelen Havale\nEURO\n15.265,00\n16.170,00\n07.08.2024\n08.08.2024 TRA2024000000319\nSatış Faturası\nMANİSA/GALABOVA BG NA\nEURO\n1.700,00\n17.870,00\n08.08.2024\n08.08.2024 TRA2024000000320\nSatış Faturası\n*MANİSA/GALABOVA BG NA\nEURO\n1.700,00\n19.570,00\n08.08.2024\n08.08.2024 TRA202400000032\nSatış Faturası\nMANİSA/GALABOVA BG NA\nEURO\n1.700,00\n21.270,00\n08.08.2024\n08.08.2024 TRA2024000000322\nSauş Faturası\nMANİSA/GALABOVA BG NA\nEURO\n1.700,00\n22.970,00\n08.08.2024\n12.08.2024 TRA2024000000327\nSatış Faturası\nMANİSA/GALABOVA BG NA\nEURO\n2.250,00\n25.220,00\n12.08.2024\n12.08.2024 TRA2024000000328\nSatış Faturası\n*MANİSA/GALABOVA BG NA\nEURC\n2.250,00\n27.470,00\n12.08.2024\n12.08.2024 TRA2024000000329\nSatış Faturası\nMANİSA/GALABOVA BG NA\nEURO\n1.700,00\n29.170,00\n12.08.2024\n12.08.2024 TRA2024000000330\nSatış Faturası\nMANİSA/GALABOVA BG NA\nEURO\n2.250,00\n31.420,00\n12.08.2024\n12.08.2024 TRA2024000000331\nSatış Faturası\nMANİSA/GALABOVA BG NA\nEURO\n1.700,00\n33.120,00\n12.08.2024\n12.08.2024 TRA2024000000332\nSatış Faturası\nMANİSA/GALABOVA BG NA\nEURO\n2.250,00\n35.370,00\n12.08.2024\n13.08.2024 TRA2024000000334\nSauş Faturası\n*MANİSA/GALABOVA BG NA\nEURO\n1.700,00\n37.070,00\n13.08.2024\n13.08.2024 TRA2024000000335\nSatış Faturası\n*MANİSA/GALABOVA BG NA\nEURO\n1.700,00\n38.770,00\n13.08.2024\n13.08.2024 TRA2024000000336\nSatış Faturası\n*MANİSA/GALABOVA BG NA\nEURO\n1.700,00\n40.470,00\n13.08.2024\n14.08.2024\n0000000331\nGelen Havale\nEURO\n29.605,00\n10.865,00\n14.08.2024\n15.08.2024 TRA2024000000338\nSatış Faturası\nMANİSA/GALABOVA BG NA\nEURO\n1.700,00\nCari Hesap Ekstresi\nFirma : KUMSAL TRANSPORT LOJ. ULUSLARARASITAŞIMACILIK SAN. TİC. LTD. ŞTİ.\nSayfa No : 2/2\nRapor Tarihi : 02.09.2024 - 11:53\nCari Kodu : 120 755\nCari Adı : TIBIEL EOOD\nTarih\nEvrak No\nEvrak Türü\nAçıklama\nDvz. Cinsi\nBorç\nAlacak\nBakiye B/A\nVade Tarihi\n28.08.2024 TRA2024000000362\nSatış Faturası\n*MANİSA/GALABOVA BG NA\nEURO\n1.700,00\n39.115,00\n28.08.2024\n28.08.2024 TRA2024000000363\nSauş Faturası\nMANİSA/GALABOVA BG NA\nEURO\n1.700,00\n40.815,00\n28.08.2024\n28.08.2024 TRA2024000000364\nSatış Faturası\n*MANİSA/GALABOVA BG NA\nEURO\n1.700,00\n42.515.00\n28.08.2024\n30.08.2024\n0000000352\nGelen Havale\nEURO\n19.865,00\n22.650,00\n30.08.2024\nToplam Tutarlar :\n113.400,00\n90.750,00\n22.660,00\nB"]}