{"attachments":["Proforma_faktura_Recoal.pdf"],"text":"----- Препратено писмо от tbl_ood@mail.bg -----\n\nДата: 07.02.2014 в 11:23\nПодател: Recoal AD (recoal@wautelet.net)\nОтносно: Recoal Proforma\nПолучател: tbl_ood@mail.bg \n\n\n\n\nЗдравейте,\n\nПриложено изпращам Проформа фактура з доставка на въглища, съгласно договор.\n\n \n\nУспешен ден,\n\n \n\nrecoal@wautelet.net <mailto:recoal@wautelet.net> \n\nRecoal AD\n\nBulgaria\n\nPernik 2300\n\nMail box №81\n\n359 882 52 52 43\n\nGalina Ananieva\n\n \n\n\n\n-------------------------------------\nMail.BG <http://mail.bg> : Безплатен e-mail адрес. Най-добрите характеристики на българския пазар - 20 GB пощенска кутия, 1 GB прикрепен файл, безплатен POP3, мобилна версия, SMS известяване и други.","subject":"FWD: Recoal Proforma","date":"2014-02-07T15:09:39.000Z","to":[{"address":"","name":"Neli Lazova"}],"attachmentsData":["Проформа фактура\nНомер:\n0000000001\nДата:\n07.02.2014\nПолучатель\n\"ТИБИЕЛ' ЕООД\nДоставчик\n\"РЕКОУЛ\" АД\nДДС №\nBG106588084\nДДС №\nBG113550568\nИдент. №\n106588084\nИдент. №\n113550568\nГрад\nПЛ. \"СВЕТИ ИВАН РИЛСКИ\" 1\nГрад\nПЕРНИК\nАдрес\nПЕРНИК\nАдрес\nУЛ. \"СВ.СВ.КИРИЛ И МЕТОДИЙ\"2/12В\nМОЛ\nДИМИТЪР ИВАНОВ\nМОЛ\nФИЛИП УОТЛЕ\nТелефон\nТелефон\nNo\nКод\nНаименование на стоката/услугата\nМярка\nКоличество\nЦена\nСума\n1\nСЪГЛАСНО ДОГОВОР ЗА ДОСТАВКА НА\nбр\n1,00 18 750,0000\n118 750,00\nВЪГЛИЩА\nДанъчна основа:\n118 750,00\nДДС 20%:\n23 750,00\nСума за плащане: 142 500,00\nСловом: Сто четиридесет и две хиляди и петстотин лв.\nДата на данъчно събитие:\n07.02.2014\nПлащане:\nПо сметка\nОснование на сделката:\nIBAN:\nBG63BUIB78371024533400\nОписание на сделката:\nБанка:\nСИБАНК АД\nМясто на сделката:\nБанков код: BUIBBGSF\nПолучил:\nСъставил: Галина Ананиева\nПрограмен продукт Microinvest Invoice Pro, тел.088/1344304, http://www.microinvest.net\n1"]}